tests/__init__.py
tests/unit/__init__.py
tests/unit/test_subcommands.py
tests/unit/test_tower.py
tw_pywrap/__init__.py
tw_pywrap/cli.py
tw_pywrap/computeenvs.py
tw_pywrap/helper.py
tw_pywrap/overwrite.py
tw_pywrap/pipelines.py
tw_pywrap/tower.py
tw_pywrap/utils.py
tw_pywrap-0.1.1.dist-info/LICENSE.txt
tw_pywrap-0.1.1.dist-info/METADATA
tw_pywrap-0.1.1.dist-info/WHEEL
tw_pywrap-0.1.1.dist-info/top_level.txt
tw_pywrap-0.1.1.dist-info/RECORD
